spotpris2/BusManager.py
spotpris2/MediaPlayer2.py
spotpris2/__init__.py
spotpris2/__main__.py
spotpris2/util.py
spotpris2/html/success.html
spotpris2/mpris/mpris-dbus-interface.xml
spotpris2/mpris/org.mpris.MediaPlayer2.Player.xml
spotpris2/mpris/org.mpris.MediaPlayer2.xml
SpotPRIS2-0.4.1.dist-info/LICENSE.txt
SpotPRIS2-0.4.1.dist-info/METADATA
SpotPRIS2-0.4.1.dist-info/WHEEL
SpotPRIS2-0.4.1.dist-info/entry_points.txt
SpotPRIS2-0.4.1.dist-info/top_level.txt
SpotPRIS2-0.4.1.dist-info/RECORD
