Metadata-Version: 2.1
Name: SpotPRIS2
Version: 0.4.1
Summary: MPRIS2 interface for Spotify Connect
Home-page: https://github.com/freundTech/SpotPRIS2
Author: Adrian Freund
Author-email: adrian@freund.io
License: UNKNOWN
Platform: UNKNOWN
Classifier: Development Status :: 3 - Alpha
Classifier: Environment :: No Input/Output (Daemon)
Classifier: Intended Audience :: End Users/Desktop
Classifier: License :: OSI Approved :: MIT License
Classifier: Operating System :: POSIX :: Linux
Classifier: Programming Language :: Python :: 3 :: Only
Classifier: Topic :: Multimedia :: Sound/Audio
Requires-Python: >=3.6
Requires-Dist: PyGObject
Requires-Dist: pydbus
Requires-Dist: spotipy (>=2.8)
Requires-Dist: appdirs
